hk_bus_eta/__init__.py
hk_bus_eta/eta.py
hk_bus_eta-2.1.6.dist-info/LICENSE
hk_bus_eta-2.1.6.dist-info/METADATA
hk_bus_eta-2.1.6.dist-info/WHEEL
hk_bus_eta-2.1.6.dist-info/top_level.txt
hk_bus_eta-2.1.6.dist-info/RECORD
