Metadata-Version: 2.1
Name: hk-bus-eta
Version: 2.1.6
Summary: Query the ETA (Estimated Time of Arrival) of HK Bus/Minibus/MTR/Lightrail
Author: Chun Law (chunalw)
Author-email: <chunlaw@rocketmail.com.com>
Keywords: python,hongkong,eta,estimated time of arrival,kmb,nlb,mtr,ctb,minibus,lightrail
Classifier: Development Status :: 5 - Production/Stable
Classifier: Intended Audience :: Developers
Classifier: Programming Language :: Python :: 3
Classifier: License :: OSI Approved :: GNU General Public License v2 (GPLv2)
Classifier: Operating System :: Unix
Classifier: Operating System :: MacOS :: MacOS X
Classifier: Operating System :: Microsoft :: Windows
License-File: LICENSE
